simple_sse_client/__init__.py
simple_sse_client/simple_sse_client.py
simple_sse_client-0.1.0.dist-info/licenses/LICENSE
simple_sse_client-0.1.0.dist-info/METADATA
simple_sse_client-0.1.0.dist-info/WHEEL
simple_sse_client-0.1.0.dist-info/top_level.txt
simple_sse_client-0.1.0.dist-info/RECORD
