Metadata-Version: 2.4
Name: simple-sse-client
Version: 0.1.0
Summary: A lightweight SSE client that uses the httpx package based on httpx-sse.
Author-email: Chris Aubin <christopher@sentient.xyz>
Maintainer-email: Chris Aubin <christopher@sentient.xyz>
License-Expression: Apache-2.0
Project-URL: Homepage, https://github.com/chris-aubin-sentient/Simple-SSE-Client
Project-URL: Issues, https://github.com/chris-aubin-sentient/Simple-SSE-Client/issues
Classifier: Development Status :: 4 - Beta
Classifier: Intended Audience :: Developers
Classifier: Programming Language :: Python :: 3.9
Requires-Python: >=3.9
License-File: LICENSE
Requires-Dist: httpx==0.28.1
Dynamic: license-file
